{"bracket": [[{"id": 1, "name": "Team E1", "seed": 1, "region": "East", "isWinner": true}, {"id": 2, "name": "Team E16", "seed": 16, "region": "East", "isWinner": false}, {"id": 3, "name": "Team E8", "seed": 8, "region": "East", "isWinner": true}, {"id": 4, "name": "Team E9", "seed": 9, "region": "East", "isWinner": false}, {"id": 5, "name": "Team E5", "seed": 5, "region": "East", "isWinner": true}, {"id": 6, "name": "Team E12", "seed": 12, "region": "East", "isWinner": false}, {"id": 7, "name": "Team E4", "seed": 4, "region": "East", "isWinner": false}, {"id": 8, "name": "Team E13", "seed": 13, "region": "East", "isWinner": true}, {"id": 9, "name": "Team E6", "seed": 6, "region": "East", "isWinner": true}, {"id": 10, "name": "Team E11", "seed": 11, "region": "East", "isWinner": false}, {"id": 11, "name": "Team E3", "seed": 3, "region": "East", "isWinner": true}, {"id": 12, "name": "Team E14", "seed": 14, "region": "East", "isWinner": false}, {"id": 13, "name": "Team E7", "seed": 7, "region": "East", "isWinner": false}, {"id": 14, "name": "Team E10", "seed": 10, "region": "East", "isWinner": true}, {"id": 15, "name": "Team E2", "seed": 2, "region": "East", "isWinner": true}, {"id": 16, "name": "Team E15", "seed": 15, "region": "East", "isWinner": false}, {"id": 17, "name": "Team W1", "seed": 1, "region": "West", "isWinner": true}, {"id": 18, "name": "Team W16", "seed": 16, "region": "West", "isWinner": false}, {"id": 19, "name": "Team W8", "seed": 8, "region": "West", "isWinner": true}, {"id": 20, "name": "Team W9", "seed": 9, "region": "West", "isWinner": false}, {"id": 21, "name": "Team W5", "seed": 5, "region": "West", "isWinner": true}, {"id": 22, "name": "Team W12", "seed": 12, "region": "West", "isWinner": false}, {"id": 23, "name": "Team W4", "seed": 4, "region": "West", "isWinner": false}, {"id": 24, "name": "Team W13", "seed": 13, "region": "West", "isWinner": true}, {"id": 25, "name": "Team W6", "seed": 6, "region": "West", "isWinner": true}, {"id": 26, "name": "Team W11", "seed": 11, "region": "West", "isWinner": false}, {"id": 27, "name": "Team W3", "seed": 3, "region": "West", "isWinner": true}, {"id": 28, "name": "Team W14", "seed": 14, "region": "West", "isWinner": false}, {"id": 29, "name": "Team W7", "seed": 7, "region": "West", "isWinner": true}, {"id": 30, "name": "Team W10", "seed": 10, "region": "West", "isWinner": false}, {"id": 31, "name": "Team W2", "seed": 2, "region": "West", "isWinner": true}, {"id": 32, "name": "Team W15", "seed": 15, "region": "West", "isWinner": false}, {"id": 33, "name": "Team S1", "seed": 1, "region": "South", "isWinner": true}, {"id": 34, "name": "Team S16", "seed": 16, "region": "South", "isWinner": false}, {"id": 35, "name": "Team S8", "seed": 8, "region": "South", "isWinner": true}, {"id": 36, "name": "Team S9", "seed": 9, "region": "South", "isWinner": false}, {"id": 37, "name": "Team S5", "seed": 5, "region": "South", "isWinner": true}, {"id": 38, "name": "Team S12", "seed": 12, "region": "South", "isWinner": false}, {"id": 39, "name": "Team S4", "seed": 4, "region": "South", "isWinner": true}, {"id": 40, "name": "Team S13", "seed": 13, "region": "South", "isWinner": false}, {"id": 41, "name": "Team S6", "seed": 6, "region": "South", "isWinner": false}, {"id": 42, "name": "Team S11", "seed": 11, "region": "South", "isWinner": true}, {"id": 43, "name": "Team S3", "seed": 3, "region": "South", "isWinner": true}, {"id": 44, "name": "Team S14", "seed": 14, "region": "South", "isWinner": false}, {"id": 45, "name": "Team S7", "seed": 7, "region": "South", "isWinner": false}, {"id": 46, "name": "Team S10", "seed": 10, "region": "South", "isWinner": true}, {"id": 47, "name": "Team S2", "seed": 2, "region": "South", "isWinner": true}, {"id": 48, "name": "Team S15", "seed": 15, "region": "South", "isWinner": false}, {"id": 49, "name": "Team M1", "seed": 1, "region": "Midwest", "isWinner": true}, {"id": 50, "name": "Team M16", "seed": 16, "region": "Midwest", "isWinner": false}, {"id": 51, "name": "Team M8", "seed": 8, "region": "Midwest", "isWinner": true}, {"id": 52, "name": "Team M9", "seed": 9, "region": "Midwest", "isWinner": false}, {"id": 53, "name": "Team M5", "seed": 5, "region": "Midwest", "isWinner": true}, {"id": 54, "name": "Team M12", "seed": 12, "region": "Midwest", "isWinner": false}, {"id": 55, "name": "Team M4", "seed": 4, "region": "Midwest", "isWinner": true}, {"id": 56, "name": "Team M13", "seed": 13, "region": "Midwest", "isWinner": false}, {"id": 57, "name": "Team M6", "seed": 6, "region": "Midwest", "isWinner": true}, {"id": 58, "name": "Team M11", "seed": 11, "region": "Midwest", "isWinner": false}, {"id": 59, "name": "Team M3", "seed": 3, "region": "Midwest", "isWinner": true}, {"id": 60, "name": "Team M14", "seed": 14, "region": "Midwest", "isWinner": false}, {"id": 61, "name": "Team M7", "seed": 7, "region": "Midwest", "isWinner": true}, {"id": 62, "name": "Team M10", "seed": 10, "region": "Midwest", "isWinner": false}, {"id": 63, "name": "Team M2", "seed": 2, "region": "Midwest", "isWinner": true}, {"id": 64, "name": "Team M15", "seed": 15, "region": "Midwest", "isWinner": false}], [{"id": 1, "name": "Team E1", "seed": 1, "region": "East", "isWinner": true}, {"id": 3, "name": "Team E8", "seed": 8, "region": "East", "isWinner": false}, {"id": 5, "name": "Team E5", "seed": 5, "region": "East", "isWinner": true}, {"id": 8, "name": "Team E13", "seed": 13, "region": "East", "isWinner": false}, {"id": 9, "name": "Team E6", "seed": 6, "region": "East", "isWinner": false}, {"id": 11, "name": "Team E3", "seed": 3, "region": "East", "isWinner": true}, {"id": 14, "name": "Team E10", "seed": 10, "region": "East", "isWinner": false}, {"id": 15, "name": "Team E2", "seed": 2, "region": "East", "isWinner": true}, {"id": 17, "name": "Team W1", "seed": 1, "region": "West", "isWinner": true}, {"id": 19, "name": "Team W8", "seed": 8, "region": "West", "isWinner": false}, {"id": 21, "name": "Team W5", "seed": 5, "region": "West", "isWinner": true}, {"id": 24, "name": "Team W13", "seed": 13, "region": "West", "isWinner": false}, {"id": 25, "name": "Team W6", "seed": 6, "region": "West", "isWinner": true}, {"id": 27, "name": "Team W3", "seed": 3, "region": "West", "isWinner": false}, {"id": 29, "name": "Team W7", "seed": 7, "region": "West", "isWinner": false}, {"id": 31, "name": "Team W2", "seed": 2, "region": "West", "isWinner": true}, {"id": 33, "name": "Team S1", "seed": 1, "region": "South", "isWinner": true}, {"id": 35, "name": "Team S8", "seed": 8, "region": "South", "isWinner": false}, {"id": 37, "name": "Team S5", "seed": 5, "region": "South", "isWinner": false}, {"id": 39, "name": "Team S4", "seed": 4, "region": "South", "isWinner": true}, {"id": 42, "name": "Team S11", "seed": 11, "region": "South", "isWinner": false}, {"id": 43, "name": "Team S3", "seed": 3, "region": "South", "isWinner": true}, {"id": 46, "name": "Team S10", "seed": 10, "region": "South", "isWinner": false}, {"id": 47, "name": "Team S2", "seed": 2, "region": "South", "isWinner": true}, {"id": 49, "name": "Team M1", "seed": 1, "region": "Midwest", "isWinner": true}, {"id": 51, "name": "Team M8", "seed": 8, "region": "Midwest", "isWinner": false}, {"id": 53, "name": "Team M5", "seed": 5, "region": "Midwest", "isWinner": false}, {"id": 55, "name": "Team M4", "seed": 4, "region": "Midwest", "isWinner": true}, {"id": 57, "name": "Team M6", "seed": 6, "region": "Midwest", "isWinner": true}, {"id": 59, "name": "Team M3", "seed": 3, "region": "Midwest", "isWinner": false}, {"id": 61, "name": "Team M7", "seed": 7, "region": "Midwest", "isWinner": false}, {"id": 63, "name": "Team M2", "seed": 2, "region": "Midwest", "isWinner": true}], [{"id": 1, "name": "Team E1", "seed": 1, "region": "East", "isWinner": true}, {"id": 5, "name": "Team E5", "seed": 5, "region": "East", "isWinner": false}, {"id": 11, "name": "Team E3", "seed": 3, "region": "East", "isWinner": false}, {"id": 15, "name": "Team E2", "seed": 2, "region": "East", "isWinner": true}, {"id": 17, "name": "Team W1", "seed": 1, "region": "West", "isWinner": true}, {"id": 21, "name": "Team W5", "seed": 5, "region": "West", "isWinner": false}, {"id": 25, "name": "Team W6", "seed": 6, "region": "West", "isWinner": false}, {"id": 31, "name": "Team W2", "seed": 2, "region": "West", "isWinner": true}, {"id": 33, "name": "Team S1", "seed": 1, "region": "South", "isWinner": true}, {"id": 39, "name": "Team S4", "seed": 4, "region": "South", "isWinner": false}, {"id": 43, "name": "Team S3", "seed": 3, "region": "South", "isWinner": false}, {"id": 47, "name": "Team S2", "seed": 2, "region": "South", "isWinner": true}, {"id": 49, "name": "Team M1", "seed": 1, "region": "Midwest", "isWinner": false}, {"id": 55, "name": "Team M4", "seed": 4, "region": "Midwest", "isWinner": true}, {"id": 57, "name": "Team M6", "seed": 6, "region": "Midwest", "isWinner": true}, {"id": 63, "name": "Team M2", "seed": 2, "region": "Midwest", "isWinner": false}], [{"id": 1, "name": "Team E1", "seed": 1, "region": "East", "isWinner": true}, {"id": 15, "name": "Team E2", "seed": 2, "region": "East", "isWinner": false}, {"id": 17, "name": "Team W1", "seed": 1, "region": "West", "isWinner": true}, {"id": 31, "name": "Team W2", "seed": 2, "region": "West", "isWinner": false}, {"id": 33, "name": "Team S1", "seed": 1, "region": "South", "isWinner": false}, {"id": 47, "name": "Team S2", "seed": 2, "region": "South", "isWinner": true}, {"id": 55, "name": "Team M4", "seed": 4, "region": "Midwest", "isWinner": true}, {"id": 57, "name": "Team M6", "seed": 6, "region": "Midwest", "isWinner": false}], [{"id": 1, "name": "Team E1", "seed": 1, "region": "East", "isWinner": true}, {"id": 17, "name": "Team W1", "seed": 1, "region": "West", "isWinner": false}, {"id": 47, "name": "Team S2", "seed": 2, "region": "South", "isWinner": true}, {"id": 55, "name": "Team M4", "seed": 4, "region": "Midwest", "isWinner": false}], [{"id": 1, "name": "Team E1", "seed": 1, "region": "East", "isWinner": true}, {"id": 47, "name": "Team S2", "seed": 2, "region": "South", "isWinner": false}], [{"id": 1, "name": "Team E1", "seed": 1, "region": "East", "isWinner": false}]], "score_data": {"total_score": 1220, "breakdown": {"Round 1": {"points": 220}, "Round 2": {"points": 160}, "Round 3": {"points": 200}, "Round 4": {"points": 160}, "Round 5": {"points": 160}, "Round 6": {"points": 320}}}}